tabularjson/__init__.py
tabularjson/objects.py
tabularjson/parse.py
tabularjson/stringify.py
tabularjson/tabular.py
tabularjson/types.py
tabularjson-1.0.2.dist-info/licenses/LICENSE.md
tabularjson-1.0.2.dist-info/METADATA
tabularjson-1.0.2.dist-info/WHEEL
tabularjson-1.0.2.dist-info/top_level.txt
tabularjson-1.0.2.dist-info/RECORD
